chmcp/__init__.py
chmcp/cloud_client.py
chmcp/cloud_config.py
chmcp/cloud_tools.py
chmcp/main.py
chmcp/mcp_env.py
chmcp/mcp_server.py
chmcp-0.1.2.dist-info/METADATA
chmcp-0.1.2.dist-info/WHEEL
chmcp-0.1.2.dist-info/entry_points.txt
chmcp-0.1.2.dist-info/licenses/LICENSE
chmcp-0.1.2.dist-info/RECORD
