Metadata-Version: 2.4
Name: chmcp
Version: 0.1.2
Summary: A comprehensive Model Context Protocol (MCP) server for ClickHouse database operations and ClickHouse Cloud management.
Project-URL: Homepage, https://github.com/oualib/chmcp
Project-URL: Repository, https://github.com/oualib/chmcp
Project-URL: Documentation, https://github.com/oualib/chmcp#readme
Project-URL: Bug Tracker, https://github.com/oualib/chmcp/issues
Project-URL: Changelog, https://github.com/oualib/chmcp/releases
Author-email: Badr Ouali <badr.ouali@outlook.fr>
Maintainer-email: Badr Ouali <badr.ouali@outlook.fr>
License-Expression: Apache-2.0
License-File: LICENSE
Keywords: analytics,clickhouse,cloud,database,mcp,model-context-protocol,sql
Classifier: Development Status :: 4 - Beta
Classifier: Intended Audience :: Developers
Classifier: License :: OSI Approved :: Apache Software License
Classifier: Operating System :: OS Independent
Classifier: Programming Language :: Python :: 3
Classifier: Programming Language :: Python :: 3.12
Classifier: Programming Language :: Python :: 3.13
Classifier: Programming Language :: Python :: 3.14
Classifier: Topic :: Database
Classifier: Topic :: Software Development :: Libraries :: Python Modules
Classifier: Topic :: System :: Systems Administration
Classifier: Typing :: Typed
Requires-Python: >=3.12
Requires-Dist: clickhouse-connect>=0.8.16
Requires-Dist: mcp[cli]>=1.4.0
Requires-Dist: pip-system-certs>=4.0
Requires-Dist: python-dotenv>=1.0.1
Requires-Dist: requests>=2.31.0
Requires-Dist: uvicorn>=0.34.0
Provides-Extra: dev
Requires-Dist: black>=24.0.0; extra == 'dev'
Requires-Dist: isort>=5.13.0; extra == 'dev'
Requires-Dist: mypy>=1.8.0; extra == 'dev'
Requires-Dist: pre-commit>=3.6.0; extra == 'dev'
Requires-Dist: pytest-asyncio>=0.23.0; extra == 'dev'
Requires-Dist: pytest>=8.0.0; extra == 'dev'
Requires-Dist: ruff>=0.8.0; extra == 'dev'
Provides-Extra: docs
Requires-Dist: mkdocs-material>=9.5.0; extra == 'docs'
Requires-Dist: mkdocs>=1.5.0; extra == 'docs'
Requires-Dist: mkdocstrings[python]>=0.24.0; extra == 'docs'
Provides-Extra: test
Requires-Dist: pytest-asyncio>=0.23.0; extra == 'test'
Requires-Dist: pytest-cov>=4.0.0; extra == 'test'
Requires-Dist: pytest-mock>=3.12.0; extra == 'test'
Requires-Dist: pytest>=8.0.0; extra == 'test'
